<Properties StartupConfiguration="{EB2208B8-2EA9-6054-617B-C009E9C4DA96}|">
  <MonoDevelop.Ide.Workbench ActiveDocument="Assets/Scripts/TurnSystem/Lever.cs">
    <Files>
      <File FileName="Assets/Scripts/TurnSystem/Lever.cs" Line="22" Column="1" />
    </Files>
    <Pads>
      <Pad Id="ProjectPad">
        <State name="__root__">
          <Node name="gravityflipper" expanded="True">
            <Node name="Assets" expanded="True">
              <Node name="Scripts" expanded="True">
                <Node name="Controllers" expanded="True" />
                <Node name="NodeSystem" expanded="True" />
                <Node name="TurnSystem" expanded="True">
                  <Node name="Lever.cs" selected="True" />
                </Node>
              </Node>
            </Node>
          </Node>
        </State>
      </Pad>
    </Pads>
  </MonoDevelop.Ide.Workbench>
  <MonoDevelop.Ide.DebuggingService.PinnedWatches />
  <MonoDevelop.Ide.Workspace ActiveConfiguration="Debug" />
  <MonoDevelop.Ide.ItemProperties.Assembly-CSharp PreferredExecutionTarget="61924485-006d-4cca-9549-dff11f89ad79" />
  <MonoDevelop.Ide.DebuggingService.Breakpoints>
    <BreakpointStore />
  </MonoDevelop.Ide.DebuggingService.Breakpoints>
  <MultiItemStartupConfigurations />
</Properties>